{
  "_id": "aRE0wXIgy9YJKFtI",
  "name": "Furshark",
  "img": "modules/ponyfinder-bestiary-of-everglow/assets/portraits/waxraven_furshark.webp",
  "type": "npc",
  "system": {
    "attributes": {
      "hp": {
        "slug": "hp",
        "_modifiers": [],
        "breakdown": "Base Max HP 15",
        "totalModifier": 0,
        "value": 15,
        "temp": 0,
        "max": 15,
        "details": "",
        "negativeHealing": false,
        "unrecoverable": 0,
        "base": 15
      },
      "speed": {
        "slug": "land-speed",
        "_modifiers": [],
        "breakdown": "Base Land Speed 25",
        "totalModifier": 0,
        "total": 25,
        "value": 25,
        "otherSpeeds": [
          {
            "slug": "swim-speed",
            "_modifiers": [],
            "breakdown": "Base Swim Speed 25",
            "totalModifier": 0,
            "type": "swim",
            "label": "Swim",
            "value": 25
          }
        ],
        "details": "",
        "type": "land",
        "label": "Land Speed"
      },
      "ac": {
        "slug": "ac",
        "label": "PF2E.ArmorClassLabel",
        "value": 13,
        "totalModifier": 3,
        "dc": 13,
        "attribute": "dex",
        "breakdown": "Base DC 10, Modifier +3",
        "modifiers": [
          {
            "slug": "base",
            "label": "Modifier",
            "domains": [
              "all",
              "dex-based"
            ],
            "modifier": 3,
            "type": "untyped",
            "ability": null,
            "adjustments": [],
            "force": false,
            "enabled": true,
            "ignored": false,
            "source": null,
            "custom": false,
            "damageType": null,
            "damageCategory": null,
            "critical": null,
            "traits": [],
            "hideIfDisabled": false,
            "kind": "modifier",
            "predicate": []
          }
        ],
        "details": ""
      },
      "allSaves": {
        "value": ""
      },
      "immunities": [],
      "weaknesses": [],
      "resistances": [],
      "flanking": {
        "canFlank": true,
        "canGangUp": [],
        "flankable": true,
        "offGuardable": true
      },
      "hardness": {
        "value": 0
      },
      "reach": {
        "base": 5,
        "manipulate": 5
      },
      "shield": {
        "itemId": null,
        "name": "PF2E.ArmorTypeShield",
        "ac": 0,
        "hp": {
          "value": 0,
          "max": 0
        },
        "brokenThreshold": 0,
        "hardness": 0,
        "raised": false,
        "broken": false,
        "destroyed": false,
        "icon": "systems/pf2e/icons/actions/raise-a-shield.webp"
      },
      "doomed": {
        "value": 0,
        "max": 4
      },
      "dying": {
        "value": 0,
        "max": 4,
        "recoveryDC": 10
      },
      "wounded": {
        "value": 0,
        "max": 3
      },
      "spellDC": null,
      "classDC": {
        "value": 14
      },
      "classOrSpellDC": {
        "value": 14
      },
      "emitsSound": true
    },
    "initiative": {
      "slug": "initiative",
      "label": "Perception",
      "value": 6,
      "totalModifier": 6,
      "dc": 16,
      "attribute": "wis",
      "breakdown": "Modifier +6",
      "modifiers": [
        {
          "slug": "base",
          "label": "Modifier",
          "domains": [
            "perception",
            "wis-based",
            "all",
            "initiative"
          ],
          "modifier": 6,
          "type": "untyped",
          "ability": null,
          "adjustments": [],
          "force": false,
          "enabled": true,
          "ignored": false,
          "source": null,
          "custom": false,
          "damageType": null,
          "damageCategory": null,
          "critical": null,
          "traits": [],
          "hideIfDisabled": false,
          "kind": "modifier",
          "predicate": []
        }
      ],
      "statistic": "perception",
      "tiebreakPriority": 1
    },
    "details": {
      "languages": {
        "value": [],
        "details": ""
      },
      "level": {
        "value": 0,
        "base": 0
      },
      "blurb": "",
      "publicNotes": "<p>Along the coastal waters of Everglow, Fursharks are a common sight. Traveling in packs of two to six, they hunt, frolic, sneak, dive, and sniff in the warm sun. These creatures were created through the efforts of seaborn races working with their coastal cousins to breed a pet that could live on land and in the sea. They found one pairing that, with the aid of magic and patience, resulted in successful hybrids. Dogs and sharks. They called this new creature the Furshark. There are many varieties of furshark depending on the breed of shark they take after. Shargis, Sharriers, Sharkweilers, Sharsset Hounds are some common varieties. Eventually, some of these got out of captivity and began to roam free in the oceans and rivers of Everglow.</p>\n<p> </p>\n<p>Fursharks have a conical head with a jaw of razor sharp teeth to rip and tear into its prey. A compact body that flexes and wiggles through the waters. Four stumpy legs with webbed paws enable it to chase prey onto land. Their fur is short and sleek, covering their face and gradually receding to a rough sharky tail. Each Furshark stands about a foot to a foot and a half tall at the shoulder and are longer than they are tall. Some would call them sausage shaped, but experts call them… well they also call them sausage shaped. A wiggly backend propels it through the waves and sands where they hunt their prey.</p>\n<p> </p>\n<p>Fursharks are pack hunters that stalk the coasts and inlets of Everglow, preferring warm waters where the food and hiding places are abundant. They often duck into a hiding place and rush out to strike when the prey is near, like a living torpedo. They can even rush fish and sea life into shallower waters where they are less able to flee. They usually travel in pairs or consorts of 4 to 6 members. On rare occasions a larger consort can gather around a large and powerful Furshark, called a Big Boi. They tend to sneak up on their prey, using the waves and sea plants for cover or crouching low and crawling over the sand on their bellies. When they’re ready to strike they rush forward to bite and thrash their prey. Those that don’t die to the initial bite can bleed out over time while the Furshark watches and stalks. A lone Furshark is not much of a threat, and can be easily startled. However, a consort of hungry Fursharks can be determined and persistent predators, hounding and harassing prey far larger than any individual member. In the midst of a feeding frenzy they are deadly and dangerous. But once fed, will happily dash in and out of the waves to play, chase, and nap in the sun.</p>\n<p> </p>\n<p>They take quickly to training and are loyal and fierce companions. A Furshark can be tamed by a patient Furshark caretaker. They need pets, belly rubs, tail slaps, fresh meat, and lots of playtime. They are social creatures and perform best in a consort with playmates and family. If possible, its best to care for and train a full consort to keep them happy and socialized, but a lone Furshark with ample attention can be a fierce and loyal companion. They make excellent guard dogs, or guardfish, because they are protective of those that become part of their consort. If they claim a territory as their own, they tend to patrol the area, making sure the other fish and game don’t stray out of a designated space.</p>",
      "privateNotes": "",
      "publication": {
        "title": "",
        "authors": "",
        "license": "OGL",
        "remaster": false
      },
      "creatureType": "",
      "alliance": "opposition"
    },
    "resources": {
      "focus": {
        "value": 0,
        "max": 0,
        "cap": 3
      }
    },
    "_migration": {
      "version": 0.932,
      "previous": {
        "schema": 0.925,
        "foundry": "12.330",
        "system": "6.2.1"
      }
    },
    "abilities": {
      "str": {
        "mod": 2,
        "label": "PF2E.AbilityStr",
        "shortLabel": "PF2E.AbilityId.str"
      },
      "dex": {
        "mod": 3,
        "label": "PF2E.AbilityDex",
        "shortLabel": "PF2E.AbilityId.dex"
      },
      "con": {
        "mod": 3,
        "label": "PF2E.AbilityCon",
        "shortLabel": "PF2E.AbilityId.con"
      },
      "int": {
        "mod": -5,
        "label": "PF2E.AbilityInt",
        "shortLabel": "PF2E.AbilityId.int"
      },
      "wis": {
        "mod": 0,
        "label": "PF2E.AbilityWis",
        "shortLabel": "PF2E.AbilityId.wis"
      },
      "cha": {
        "mod": 2,
        "label": "PF2E.AbilityCha",
        "shortLabel": "PF2E.AbilityId.cha"
      }
    },
    "perception": {
      "slug": "perception",
      "label": "Perception",
      "value": 6,
      "totalModifier": 6,
      "dc": 16,
      "attribute": "wis",
      "breakdown": "Modifier +6",
      "modifiers": [
        {
          "slug": "base",
          "label": "Modifier",
          "domains": [
            "perception",
            "wis-based",
            "all"
          ],
          "modifier": 6,
          "type": "untyped",
          "ability": null,
          "adjustments": [],
          "force": false,
          "enabled": true,
          "ignored": false,
          "source": null,
          "custom": false,
          "damageType": null,
          "damageCategory": null,
          "critical": null,
          "traits": [],
          "hideIfDisabled": false,
          "kind": "modifier",
          "predicate": []
        }
      ],
      "senses": [
        {
          "type": "scent",
          "acuity": "imprecise",
          "range": 60,
          "source": null,
          "label": "Scent (Imprecise) 60 Feet",
          "emphasizeLabel": false
        }
      ],
      "vision": true,
      "details": "",
      "mod": 6
    },
    "saves": {
      "fortitude": {
        "value": 6,
        "saveDetail": "",
        "attribute": null,
        "slug": "fortitude",
        "label": "Fortitude",
        "totalModifier": 6,
        "dc": 16,
        "breakdown": "Modifier +6",
        "modifiers": [
          {
            "slug": "base",
            "label": "Modifier",
            "domains": [
              "fortitude",
              "con-based",
              "saving-throw",
              "all"
            ],
            "modifier": 6,
            "type": "untyped",
            "ability": null,
            "adjustments": [],
            "force": false,
            "enabled": true,
            "ignored": false,
            "source": null,
            "custom": false,
            "damageType": null,
            "damageCategory": null,
            "critical": null,
            "traits": [],
            "hideIfDisabled": false,
            "kind": "modifier",
            "predicate": []
          }
        ],
        "base": 6
      },
      "reflex": {
        "value": 8,
        "saveDetail": "",
        "attribute": null,
        "slug": "reflex",
        "label": "Reflex",
        "totalModifier": 8,
        "dc": 18,
        "breakdown": "Modifier +8",
        "modifiers": [
          {
            "slug": "base",
            "label": "Modifier",
            "domains": [
              "reflex",
              "dex-based",
              "saving-throw",
              "all"
            ],
            "modifier": 8,
            "type": "untyped",
            "ability": null,
            "adjustments": [],
            "force": false,
            "enabled": true,
            "ignored": false,
            "source": null,
            "custom": false,
            "damageType": null,
            "damageCategory": null,
            "critical": null,
            "traits": [],
            "hideIfDisabled": false,
            "kind": "modifier",
            "predicate": []
          }
        ],
        "base": 8
      },
      "will": {
        "value": 3,
        "saveDetail": "",
        "attribute": null,
        "slug": "will",
        "label": "Will",
        "totalModifier": 3,
        "dc": 13,
        "breakdown": "Modifier +3",
        "modifiers": [
          {
            "slug": "base",
            "label": "Modifier",
            "domains": [
              "will",
              "wis-based",
              "saving-throw",
              "all"
            ],
            "modifier": 3,
            "type": "untyped",
            "ability": null,
            "adjustments": [],
            "force": false,
            "enabled": true,
            "ignored": false,
            "source": null,
            "custom": false,
            "damageType": null,
            "damageCategory": null,
            "critical": null,
            "traits": [],
            "hideIfDisabled": false,
            "kind": "modifier",
            "predicate": []
          }
        ],
        "base": 3
      }
    },
    "skills": {
      "acrobatics": {
        "base": 5,
        "slug": "acrobatics",
        "label": "Acrobatics",
        "value": 5,
        "totalModifier": 5,
        "dc": 15,
        "attribute": "dex",
        "breakdown": "Modifier +5",
        "modifiers": [
          {
            "slug": "base",
            "label": "Modifier",
            "domains": [
              "acrobatics",
              "dex-based",
              "skill-check",
              "dex-skill-check",
              "all"
            ],
            "modifier": 5,
            "type": "untyped",
            "ability": null,
            "adjustments": [],
            "force": false,
            "enabled": true,
            "ignored": false,
            "source": null,
            "custom": false,
            "damageType": null,
            "damageCategory": null,
            "critical": null,
            "traits": [],
            "hideIfDisabled": false,
            "kind": "modifier",
            "predicate": []
          }
        ],
        "mod": 5,
        "itemId": null,
        "lore": false,
        "visible": true,
        "special": []
      },
      "arcana": {
        "base": 0,
        "slug": "arcana",
        "label": "Arcana",
        "value": 0,
        "totalModifier": 0,
        "dc": 10,
        "attribute": "int",
        "breakdown": "Modifier +0",
        "modifiers": [
          {
            "slug": "base",
            "label": "Modifier",
            "domains": [
              "arcana",
              "int-based",
              "skill-check",
              "int-skill-check",
              "all"
            ],
            "modifier": 0,
            "type": "untyped",
            "ability": null,
            "adjustments": [],
            "force": false,
            "enabled": true,
            "ignored": false,
            "source": null,
            "custom": false,
            "damageType": null,
            "damageCategory": null,
            "critical": null,
            "traits": [],
            "hideIfDisabled": false,
            "kind": "modifier",
            "predicate": []
          }
        ],
        "mod": 0,
        "itemId": null,
        "lore": false,
        "visible": true,
        "special": []
      },
      "athletics": {
        "base": 0,
        "slug": "athletics",
        "label": "Athletics",
        "value": 0,
        "totalModifier": 0,
        "dc": 10,
        "attribute": "str",
        "breakdown": "Modifier +0",
        "modifiers": [
          {
            "slug": "base",
            "label": "Modifier",
            "domains": [
              "athletics",
              "str-based",
              "skill-check",
              "str-skill-check",
              "all"
            ],
            "modifier": 0,
            "type": "untyped",
            "ability": null,
            "adjustments": [],
            "force": false,
            "enabled": true,
            "ignored": false,
            "source": null,
            "custom": false,
            "damageType": null,
            "damageCategory": null,
            "critical": null,
            "traits": [],
            "hideIfDisabled": false,
            "kind": "modifier",
            "predicate": []
          }
        ],
        "mod": 0,
        "itemId": null,
        "lore": false,
        "visible": true,
        "special": []
      },
      "crafting": {
        "base": 0,
        "slug": "crafting",
        "label": "Crafting",
        "value": 0,
        "totalModifier": 0,
        "dc": 10,
        "attribute": "int",
        "breakdown": "Modifier +0",
        "modifiers": [
          {
            "slug": "base",
            "label": "Modifier",
            "domains": [
              "crafting",
              "int-based",
              "skill-check",
              "int-skill-check",
              "all"
            ],
            "modifier": 0,
            "type": "untyped",
            "ability": null,
            "adjustments": [],
            "force": false,
            "enabled": true,
            "ignored": false,
            "source": null,
            "custom": false,
            "damageType": null,
            "damageCategory": null,
            "critical": null,
            "traits": [],
            "hideIfDisabled": false,
            "kind": "modifier",
            "predicate": []
          }
        ],
        "mod": 0,
        "itemId": null,
        "lore": false,
        "visible": true,
        "special": []
      },
      "deception": {
        "base": 0,
        "slug": "deception",
        "label": "Deception",
        "value": 0,
        "totalModifier": 0,
        "dc": 10,
        "attribute": "cha",
        "breakdown": "Modifier +0",
        "modifiers": [
          {
            "slug": "base",
            "label": "Modifier",
            "domains": [
              "deception",
              "cha-based",
              "skill-check",
              "cha-skill-check",
              "all"
            ],
            "modifier": 0,
            "type": "untyped",
            "ability": null,
            "adjustments": [],
            "force": false,
            "enabled": true,
            "ignored": false,
            "source": null,
            "custom": false,
            "damageType": null,
            "damageCategory": null,
            "critical": null,
            "traits": [],
            "hideIfDisabled": false,
            "kind": "modifier",
            "predicate": []
          }
        ],
        "mod": 0,
        "itemId": null,
        "lore": false,
        "visible": true,
        "special": []
      },
      "diplomacy": {
        "base": 0,
        "slug": "diplomacy",
        "label": "Diplomacy",
        "value": 0,
        "totalModifier": 0,
        "dc": 10,
        "attribute": "cha",
        "breakdown": "Modifier +0",
        "modifiers": [
          {
            "slug": "base",
            "label": "Modifier",
            "domains": [
              "diplomacy",
              "cha-based",
              "skill-check",
              "cha-skill-check",
              "all"
            ],
            "modifier": 0,
            "type": "untyped",
            "ability": null,
            "adjustments": [],
            "force": false,
            "enabled": true,
            "ignored": false,
            "source": null,
            "custom": false,
            "damageType": null,
            "damageCategory": null,
            "critical": null,
            "traits": [],
            "hideIfDisabled": false,
            "kind": "modifier",
            "predicate": []
          }
        ],
        "mod": 0,
        "itemId": null,
        "lore": false,
        "visible": true,
        "special": []
      },
      "intimidation": {
        "base": 0,
        "slug": "intimidation",
        "label": "Intimidation",
        "value": 0,
        "totalModifier": 0,
        "dc": 10,
        "attribute": "cha",
        "breakdown": "Modifier +0",
        "modifiers": [
          {
            "slug": "base",
            "label": "Modifier",
            "domains": [
              "intimidation",
              "cha-based",
              "skill-check",
              "cha-skill-check",
              "all"
            ],
            "modifier": 0,
            "type": "untyped",
            "ability": null,
            "adjustments": [],
            "force": false,
            "enabled": true,
            "ignored": false,
            "source": null,
            "custom": false,
            "damageType": null,
            "damageCategory": null,
            "critical": null,
            "traits": [],
            "hideIfDisabled": false,
            "kind": "modifier",
            "predicate": []
          }
        ],
        "mod": 0,
        "itemId": null,
        "lore": false,
        "visible": true,
        "special": []
      },
      "medicine": {
        "base": 0,
        "slug": "medicine",
        "label": "Medicine",
        "value": 0,
        "totalModifier": 0,
        "dc": 10,
        "attribute": "wis",
        "breakdown": "Modifier +0",
        "modifiers": [
          {
            "slug": "base",
            "label": "Modifier",
            "domains": [
              "medicine",
              "wis-based",
              "skill-check",
              "wis-skill-check",
              "all"
            ],
            "modifier": 0,
            "type": "untyped",
            "ability": null,
            "adjustments": [],
            "force": false,
            "enabled": true,
            "ignored": false,
            "source": null,
            "custom": false,
            "damageType": null,
            "damageCategory": null,
            "critical": null,
            "traits": [],
            "hideIfDisabled": false,
            "kind": "modifier",
            "predicate": []
          }
        ],
        "mod": 0,
        "itemId": null,
        "lore": false,
        "visible": true,
        "special": []
      },
      "nature": {
        "base": 0,
        "slug": "nature",
        "label": "Nature",
        "value": 0,
        "totalModifier": 0,
        "dc": 10,
        "attribute": "wis",
        "breakdown": "Modifier +0",
        "modifiers": [
          {
            "slug": "base",
            "label": "Modifier",
            "domains": [
              "nature",
              "wis-based",
              "skill-check",
              "wis-skill-check",
              "all"
            ],
            "modifier": 0,
            "type": "untyped",
            "ability": null,
            "adjustments": [],
            "force": false,
            "enabled": true,
            "ignored": false,
            "source": null,
            "custom": false,
            "damageType": null,
            "damageCategory": null,
            "critical": null,
            "traits": [],
            "hideIfDisabled": false,
            "kind": "modifier",
            "predicate": []
          }
        ],
        "mod": 0,
        "itemId": null,
        "lore": false,
        "visible": true,
        "special": []
      },
      "occultism": {
        "base": 0,
        "slug": "occultism",
        "label": "Occultism",
        "value": 0,
        "totalModifier": 0,
        "dc": 10,
        "attribute": "int",
        "breakdown": "Modifier +0",
        "modifiers": [
          {
            "slug": "base",
            "label": "Modifier",
            "domains": [
              "occultism",
              "int-based",
              "skill-check",
              "int-skill-check",
              "all"
            ],
            "modifier": 0,
            "type": "untyped",
            "ability": null,
            "adjustments": [],
            "force": false,
            "enabled": true,
            "ignored": false,
            "source": null,
            "custom": false,
            "damageType": null,
            "damageCategory": null,
            "critical": null,
            "traits": [],
            "hideIfDisabled": false,
            "kind": "modifier",
            "predicate": []
          }
        ],
        "mod": 0,
        "itemId": null,
        "lore": false,
        "visible": true,
        "special": []
      },
      "performance": {
        "base": 0,
        "slug": "performance",
        "label": "Performance",
        "value": 0,
        "totalModifier": 0,
        "dc": 10,
        "attribute": "cha",
        "breakdown": "Modifier +0",
        "modifiers": [
          {
            "slug": "base",
            "label": "Modifier",
            "domains": [
              "performance",
              "cha-based",
              "skill-check",
              "cha-skill-check",
              "all"
            ],
            "modifier": 0,
            "type": "untyped",
            "ability": null,
            "adjustments": [],
            "force": false,
            "enabled": true,
            "ignored": false,
            "source": null,
            "custom": false,
            "damageType": null,
            "damageCategory": null,
            "critical": null,
            "traits": [],
            "hideIfDisabled": false,
            "kind": "modifier",
            "predicate": []
          }
        ],
        "mod": 0,
        "itemId": null,
        "lore": false,
        "visible": true,
        "special": []
      },
      "religion": {
        "base": 0,
        "slug": "religion",
        "label": "Religion",
        "value": 0,
        "totalModifier": 0,
        "dc": 10,
        "attribute": "wis",
        "breakdown": "Modifier +0",
        "modifiers": [
          {
            "slug": "base",
            "label": "Modifier",
            "domains": [
              "religion",
              "wis-based",
              "skill-check",
              "wis-skill-check",
              "all"
            ],
            "modifier": 0,
            "type": "untyped",
            "ability": null,
            "adjustments": [],
            "force": false,
            "enabled": true,
            "ignored": false,
            "source": null,
            "custom": false,
            "damageType": null,
            "damageCategory": null,
            "critical": null,
            "traits": [],
            "hideIfDisabled": false,
            "kind": "modifier",
            "predicate": []
          }
        ],
        "mod": 0,
        "itemId": null,
        "lore": false,
        "visible": true,
        "special": []
      },
      "society": {
        "base": 0,
        "slug": "society",
        "label": "Society",
        "value": 0,
        "totalModifier": 0,
        "dc": 10,
        "attribute": "int",
        "breakdown": "Modifier +0",
        "modifiers": [
          {
            "slug": "base",
            "label": "Modifier",
            "domains": [
              "society",
              "int-based",
              "skill-check",
              "int-skill-check",
              "all"
            ],
            "modifier": 0,
            "type": "untyped",
            "ability": null,
            "adjustments": [],
            "force": false,
            "enabled": true,
            "ignored": false,
            "source": null,
            "custom": false,
            "damageType": null,
            "damageCategory": null,
            "critical": null,
            "traits": [],
            "hideIfDisabled": false,
            "kind": "modifier",
            "predicate": []
          }
        ],
        "mod": 0,
        "itemId": null,
        "lore": false,
        "visible": true,
        "special": []
      },
      "stealth": {
        "base": 5,
        "slug": "stealth",
        "label": "Stealth",
        "value": 5,
        "totalModifier": 5,
        "dc": 15,
        "attribute": "dex",
        "breakdown": "Modifier +5",
        "modifiers": [
          {
            "slug": "base",
            "label": "Modifier",
            "domains": [
              "stealth",
              "dex-based",
              "skill-check",
              "dex-skill-check",
              "all"
            ],
            "modifier": 5,
            "type": "untyped",
            "ability": null,
            "adjustments": [],
            "force": false,
            "enabled": true,
            "ignored": false,
            "source": null,
            "custom": false,
            "damageType": null,
            "damageCategory": null,
            "critical": null,
            "traits": [],
            "hideIfDisabled": false,
            "kind": "modifier",
            "predicate": []
          }
        ],
        "mod": 5,
        "itemId": null,
        "lore": false,
        "visible": true,
        "special": []
      },
      "survival": {
        "base": 0,
        "slug": "survival",
        "label": "Survival",
        "value": 0,
        "totalModifier": 0,
        "dc": 10,
        "attribute": "wis",
        "breakdown": "Modifier +0",
        "modifiers": [
          {
            "slug": "base",
            "label": "Modifier",
            "domains": [
              "survival",
              "wis-based",
              "skill-check",
              "wis-skill-check",
              "all"
            ],
            "modifier": 0,
            "type": "untyped",
            "ability": null,
            "adjustments": [],
            "force": false,
            "enabled": true,
            "ignored": false,
            "source": null,
            "custom": false,
            "damageType": null,
            "damageCategory": null,
            "critical": null,
            "traits": [],
            "hideIfDisabled": false,
            "kind": "modifier",
            "predicate": []
          }
        ],
        "mod": 0,
        "itemId": null,
        "lore": false,
        "visible": true,
        "special": []
      },
      "thievery": {
        "base": 0,
        "slug": "thievery",
        "label": "Thievery",
        "value": 0,
        "totalModifier": 0,
        "dc": 10,
        "attribute": "dex",
        "breakdown": "Modifier +0",
        "modifiers": [
          {
            "slug": "base",
            "label": "Modifier",
            "domains": [
              "thievery",
              "dex-based",
              "skill-check",
              "dex-skill-check",
              "all"
            ],
            "modifier": 0,
            "type": "untyped",
            "ability": null,
            "adjustments": [],
            "force": false,
            "enabled": true,
            "ignored": false,
            "source": null,
            "custom": false,
            "damageType": null,
            "damageCategory": null,
            "critical": null,
            "traits": [],
            "hideIfDisabled": false,
            "kind": "modifier",
            "predicate": []
          }
        ],
        "mod": 0,
        "itemId": null,
        "lore": false,
        "visible": true,
        "special": []
      }
    },
    "traits": {
      "value": [
        "amphibious",
        "animal"
      ],
      "rarity": "common",
      "size": {
        "value": "sm",
        "length": 5,
        "width": 5
      }
    },
    "autoChanges": {},
    "customModifiers": {},
    "actions": [
      {
        "slug": "jaws",
        "_modifiers": [
          {
            "slug": "base",
            "label": "Modifier",
            "domains": [],
            "modifier": 7,
            "type": "untyped",
            "ability": null,
            "adjustments": [],
            "alterations": [],
            "force": false,
            "enabled": true,
            "ignored": false,
            "source": null,
            "custom": false,
            "damageType": null,
            "damageCategory": null,
            "predicate": [],
            "critical": null,
            "traits": [],
            "hideIfDisabled": false,
            "kind": "modifier"
          }
        ],
        "breakdown": "Modifier +7",
        "totalModifier": 7,
        "label": "Jaws",
        "type": "strike",
        "glyph": "1",
        "description": "",
        "sourceId": "B8YMO12FbiT3vK1y",
        "attackRollType": "PF2E.NPCAttackMelee",
        "additionalEffects": [],
        "item": {
          "_id": "B8YMO12FbiT3vK1y",
          "name": "Jaws",
          "type": "melee",
          "img": "systems/pf2e/icons/default-icons/melee.svg",
          "system": {
            "description": {
              "value": "",
              "gm": ""
            },
            "publication": {
              "title": "",
              "authors": "",
              "license": "OGL",
              "remaster": false
            },
            "rules": [],
            "slug": null,
            "traits": {
              "otherTags": [],
              "value": [
                "agile",
                "deadly-d6"
              ]
            },
            "_migration": {
              "version": 0.932,
              "previous": {
                "foundry": "12.330",
                "system": "6.2.1",
                "schema": 0.925
              }
            },
            "damageRolls": {
              "fHwXaobRC443FaxU": {
                "damage": "1d6 + 2",
                "damageType": "slashing",
                "category": null
              }
            },
            "bonus": {
              "value": 7
            },
            "attackEffects": {
              "value": []
            }
          },
          "effects": [],
          "folder": null,
          "sort": 0,
          "ownership": {
            "default": 0,
            "oVmqWh8fUdNNBRRt": 3
          },
          "flags": {
            "pf2e": {
              "rulesSelections": {},
              "itemGrants": {}
            }
          },
          "_stats": {
            "coreVersion": "12.331",
            "systemId": "pf2e",
            "systemVersion": "6.2.1",
            "createdTime": null,
            "modifiedTime": null,
            "lastModifiedBy": null,
            "compendiumSource": null,
            "duplicateSource": null
          }
        },
        "weapon": {
          "_id": "B8YMO12FbiT3vK1y",
          "name": "Jaws",
          "type": "melee",
          "img": "systems/pf2e/icons/default-icons/melee.svg",
          "system": {
            "description": {
              "value": "",
              "gm": ""
            },
            "publication": {
              "title": "",
              "authors": "",
              "license": "OGL",
              "remaster": false
            },
            "rules": [],
            "slug": null,
            "traits": {
              "otherTags": [],
              "value": [
                "agile",
                "deadly-d6"
              ]
            },
            "_migration": {
              "version": 0.932,
              "previous": {
                "foundry": "12.330",
                "system": "6.2.1",
                "schema": 0.925
              }
            },
            "damageRolls": {
              "fHwXaobRC443FaxU": {
                "damage": "1d6 + 2",
                "damageType": "slashing",
                "category": null
              }
            },
            "bonus": {
              "value": 7
            },
            "attackEffects": {
              "value": []
            }
          },
          "effects": [],
          "folder": null,
          "sort": 0,
          "ownership": {
            "default": 0,
            "oVmqWh8fUdNNBRRt": 3
          },
          "flags": {
            "pf2e": {
              "rulesSelections": {},
              "itemGrants": {}
            }
          },
          "_stats": {
            "coreVersion": "12.331",
            "systemId": "pf2e",
            "systemVersion": "6.2.1",
            "createdTime": null,
            "modifiedTime": null,
            "lastModifiedBy": null,
            "compendiumSource": null,
            "duplicateSource": null
          }
        },
        "canStrike": true,
        "options": [
          "self:action:slug:strike",
          "melee",
          "agile",
          "deadly-d6"
        ],
        "traits": [
          {
            "name": "attack",
            "label": "Attack",
            "description": "PF2E.TraitDescriptionAttack"
          },
          {
            "name": "agile",
            "label": "Agile",
            "description": "PF2E.TraitDescriptionAgile"
          },
          {
            "name": "deadly-d6",
            "label": "Deadly d6",
            "description": "PF2E.TraitDescriptionDeadly"
          }
        ],
        "variants": [
          {
            "label": "Strike +7"
          },
          {
            "label": "+3 (MAP -4)"
          },
          {
            "label": "-1 (MAP -8)"
          }
        ],
        "ready": true,
        "success": "",
        "criticalSuccess": ""
      }
    ],
    "spellcasting": {
      "rituals": {
        "dc": 0
      }
    }
  },
  "prototypeToken": {
    "name": "Furshark",
    "displayName": 20,
    "actorLink": false,
    "appendNumber": false,
    "prependAdjective": true,
    "width": 1,
    "height": 1,
    "texture": {
      "src": "modules/ponyfinder-bestiary-of-everglow/assets/tokens/furshark%20token.webp",
      "anchorX": 0.5,
      "anchorY": 0.5,
      "offsetX": 0,
      "offsetY": 0,
      "fit": "contain",
      "scaleX": 1.3,
      "scaleY": 1.3,
      "rotation": 0,
      "tint": "#ffffff",
      "alphaThreshold": 0.75
    },
    "hexagonalShape": 0,
    "lockRotation": false,
    "rotation": 0,
    "alpha": 1,
    "disposition": -1,
    "displayBars": 20,
    "bar1": {
      "attribute": "attributes.hp"
    },
    "bar2": {
      "attribute": null
    },
    "light": {
      "negative": false,
      "priority": 0,
      "alpha": 0.5,
      "angle": 360,
      "bright": 0,
      "color": null,
      "coloration": 1,
      "dim": 0,
      "attenuation": 0.5,
      "luminosity": 0.5,
      "saturation": 0,
      "contrast": 0,
      "shadows": 0,
      "animation": {
        "type": null,
        "speed": 5,
        "intensity": 5,
        "reverse": false
      },
      "darkness": {
        "min": 0,
        "max": 1
      }
    },
    "sight": {
      "enabled": false,
      "range": 0,
      "angle": 360,
      "visionMode": "basic",
      "color": null,
      "attenuation": 0.1,
      "brightness": 0,
      "saturation": 0,
      "contrast": 0
    },
    "detectionModes": [],
    "occludable": {
      "radius": 0
    },
    "ring": {
      "enabled": false,
      "colors": {
        "ring": null,
        "background": null
      },
      "effects": 0,
      "subject": {
        "scale": 1,
        "texture": null
      }
    },
    "flags": {
      "pf2e": {
        "linkToActorSize": true,
        "autoscale": false
      }
    },
    "randomImg": false
  },
  "items": [
    {
      "_id": "mIcWlBqXYq3D1HTH",
      "name": "Defensive Wiggle",
      "type": "action",
      "img": "systems/pf2e/icons/default-icons/action.svg",
      "system": {
        "description": {
          "gm": "",
          "value": "<p><strong>Trigger</strong>: A creature scores success on an attack roll against the Furshark.</p>\n<hr />\n<p><strong>Effect</strong>: The Furshark gains Resistance 4 to the triggering attack. This may not be used again until the Furshark rolls a critical success with an attack.</p>",
          "addenda": [],
          "override": null
        },
        "rules": [
          {
            "key": "Resistance",
            "value": 4,
            "type": [
              "all-damage"
            ],
            "predicate": [
              "defensive-wiggle"
            ],
            "slug": null,
            "priority": 100,
            "ignored": false,
            "mode": "add",
            "exceptions": [],
            "override": false,
            "doubleVs": []
          },
          {
            "key": "RollOption",
            "option": "defensive-wiggle",
            "toggleable": true,
            "slug": null,
            "priority": 50,
            "ignored": false,
            "predicate": [],
            "domain": "all",
            "phase": "applyAEs",
            "suboptions": [],
            "mergeable": false,
            "value": false
          }
        ],
        "slug": null,
        "_migration": {
          "version": 0.932,
          "lastMigration": null,
          "previous": {
            "schema": 0.925,
            "foundry": "12.330",
            "system": "6.2.1"
          }
        },
        "traits": {
          "otherTags": [],
          "value": [],
          "toggles": {
            "mindshift": null
          }
        },
        "publication": {
          "title": "",
          "authors": "",
          "license": "OGL",
          "remaster": false
        },
        "actionType": {
          "value": "reaction"
        },
        "category": null,
        "actions": {
          "value": null
        },
        "deathNote": false,
        "requirements": {
          "value": ""
        },
        "trigger": {
          "value": ""
        },
        "selfEffect": null
      },
      "effects": [],
      "folder": null,
      "sort": 0,
      "ownership": {
        "default": 0,
        "oVmqWh8fUdNNBRRt": 3
      },
      "flags": {
        "pf2e": {
          "rulesSelections": {},
          "itemGrants": {}
        }
      },
      "_stats": {
        "coreVersion": "12.331",
        "systemId": "pf2e",
        "systemVersion": "6.2.1",
        "createdTime": null,
        "modifiedTime": null,
        "lastModifiedBy": null,
        "compendiumSource": null,
        "duplicateSource": null
      }
    },
    {
      "_id": "B8YMO12FbiT3vK1y",
      "name": "Jaws",
      "type": "melee",
      "img": "systems/pf2e/icons/default-icons/melee.svg",
      "system": {
        "description": {
          "value": "",
          "gm": ""
        },
        "publication": {
          "title": "",
          "authors": "",
          "license": "OGL",
          "remaster": false
        },
        "rules": [],
        "slug": null,
        "traits": {
          "otherTags": [],
          "value": [
            "agile",
            "deadly-d6"
          ]
        },
        "_migration": {
          "version": 0.932,
          "previous": {
            "foundry": "12.330",
            "system": "6.2.1",
            "schema": 0.925
          }
        },
        "damageRolls": {
          "fHwXaobRC443FaxU": {
            "damage": "1d6 + 2",
            "damageType": "slashing",
            "category": null
          }
        },
        "bonus": {
          "value": 7
        },
        "attackEffects": {
          "value": []
        }
      },
      "effects": [],
      "folder": null,
      "sort": 0,
      "ownership": {
        "default": 0,
        "oVmqWh8fUdNNBRRt": 3
      },
      "flags": {
        "pf2e": {
          "rulesSelections": {},
          "itemGrants": {}
        }
      },
      "_stats": {
        "coreVersion": "12.331",
        "systemId": "pf2e",
        "systemVersion": "6.2.1",
        "createdTime": null,
        "modifiedTime": null,
        "lastModifiedBy": null,
        "compendiumSource": null,
        "duplicateSource": null
      }
    },
    {
      "_id": "LKtp8ihM0iA6FrYH",
      "name": "Thrash",
      "type": "action",
      "img": "systems/pf2e/icons/default-icons/action.svg",
      "system": {
        "description": {
          "gm": "",
          "value": "<p><strong>Requirements</strong> The Furshark hit with a jaws Strike on its most recent action this turn.</p><hr /><p><strong>Effect</strong> The Furshark inflicts @Damage[1d4[bleed]]{1d4 persistent bleed} Damage to the last creature hit by its bite attack.</p>",
          "addenda": [],
          "override": null
        },
        "rules": [],
        "slug": null,
        "_migration": {
          "version": 0.932,
          "lastMigration": null,
          "previous": {
            "schema": 0.925,
            "foundry": "12.330",
            "system": "6.2.1"
          }
        },
        "traits": {
          "otherTags": [],
          "value": [],
          "toggles": {
            "mindshift": null
          }
        },
        "publication": {
          "title": "",
          "authors": "",
          "license": "OGL",
          "remaster": false
        },
        "actionType": {
          "value": "action"
        },
        "category": null,
        "actions": {
          "value": 1
        },
        "deathNote": false,
        "requirements": {
          "value": ""
        },
        "trigger": {
          "value": ""
        },
        "selfEffect": null
      },
      "effects": [],
      "folder": null,
      "sort": 0,
      "ownership": {
        "default": 0,
        "oVmqWh8fUdNNBRRt": 3
      },
      "flags": {
        "pf2e": {
          "rulesSelections": {},
          "itemGrants": {}
        }
      },
      "_stats": {
        "coreVersion": "12.331",
        "systemId": "pf2e",
        "systemVersion": "6.2.1",
        "createdTime": null,
        "modifiedTime": null,
        "lastModifiedBy": null,
        "compendiumSource": null,
        "duplicateSource": null
      }
    }
  ],
  "effects": [],
  "folder": null,
  "sort": 0,
  "ownership": {
    "default": 0,
    "7V80iZREAvj5ZaV4": 3
  },
  "flags": {
    "core": {},
    "pf2e": {
      "rollOptions": {
        "all": {
          "self:type:npc": true,
          "self:signature:df84c1fd-23d6-57dd-8d26-8b9850fb372d": true,
          "self:creature": true,
          "self:level:0": true,
          "self:mode:living": true,
          "self:trait:amphibious": true,
          "self:trait:animal": true,
          "self:armored": false,
          "self:size:1": true,
          "self:size:small": true,
          "hp-remaining:15": true,
          "hp-percent:100": true,
          "speed:land": true,
          "speed:swim": true,
          "self:signature:a35ddf46-6f38-5da0-97ac-0302f0fdea62": true,
          "self:signature:762fe792-b1a7-5033-93fb-24b7f7b409b8": true
        }
      },
      "trackedItems": {},
      "lootable": false
    }
  },
  "_stats": {
    "coreVersion": "12.331",
    "systemId": "pf2e",
    "systemVersion": "6.2.1",
    "createdTime": 1723762245334,
    "modifiedTime": 1723781936973,
    "lastModifiedBy": "7V80iZREAvj5ZaV4",
    "compendiumSource": "Compendium.ponyfinder-bestiary-of-everglow.ponyfinder-bestiary-npc-gallery.Actor.aRE0wXIgy9YJKFtI",
    "duplicateSource": null
  }
}